jrnl/__init__.py
jrnl/__main__.py
jrnl/__version__.py
jrnl/args.py
jrnl/color.py
jrnl/commands.py
jrnl/config.py
jrnl/controller.py
jrnl/editor.py
jrnl/encryption/BaseEncryption.py
jrnl/encryption/BaseKeyEncryption.py
jrnl/encryption/BasePasswordEncryption.py
jrnl/encryption/Jrnlv1Encryption.py
jrnl/encryption/Jrnlv2Encryption.py
jrnl/encryption/NoEncryption.py
jrnl/encryption/__init__.py
jrnl/exception.py
jrnl/install.py
jrnl/journals/DayOneJournal.py
jrnl/journals/Entry.py
jrnl/journals/FolderJournal.py
jrnl/journals/Journal.py
jrnl/journals/__init__.py
jrnl/keyring.py
jrnl/main.py
jrnl/messages/Message.py
jrnl/messages/MsgStyle.py
jrnl/messages/MsgText.py
jrnl/messages/__init__.py
jrnl/os_compat.py
jrnl/output.py
jrnl/override.py
jrnl/path.py
jrnl/plugins/__init__.py
jrnl/plugins/calendar_heatmap_exporter.py
jrnl/plugins/dates_exporter.py
jrnl/plugins/fancy_exporter.py
jrnl/plugins/jrnl_importer.py
jrnl/plugins/json_exporter.py
jrnl/plugins/markdown_exporter.py
jrnl/plugins/tag_exporter.py
jrnl/plugins/text_exporter.py
jrnl/plugins/util.py
jrnl/plugins/xml_exporter.py
jrnl/plugins/yaml_exporter.py
jrnl/prompt.py
jrnl/templates/sample.template
jrnl/time.py
jrnl/upgrade.py
jrnl-4.2.1.dist-info/LICENSE.md
jrnl-4.2.1.dist-info/METADATA
jrnl-4.2.1.dist-info/WHEEL
jrnl-4.2.1.dist-info/entry_points.txt
jrnl-4.2.1.dist-info/RECORD
