Metadata-Version: 2.3
Name: jrnl
Version: 4.2.1
Summary: Collect your thoughts and notes without leaving the command line.
License: GPL-3.0-only
Author: jrnl contributors
Author-email: maintainers@jrnl.sh
Maintainer: Jonathan Wren and Micah Ellison
Maintainer-email: maintainers@jrnl.sh
Requires-Python: >=3.10.0,<3.14
Classifier: Environment :: Console
Classifier: License :: OSI Approved :: GNU General Public License v3 (GPLv3)
Classifier: Operating System :: OS Independent
Classifier: Programming Language :: Python :: 3
Classifier: Programming Language :: Python :: 3.10
Classifier: Programming Language :: Python :: 3.11
Classifier: Programming Language :: Python :: 3.12
Classifier: Programming Language :: Python :: 3.13
Classifier: Topic :: Office/Business :: News/Diary
Requires-Dist: colorama (>=0.4)
Requires-Dist: cryptography (>=3.0)
Requires-Dist: keyring (>=21.0)
Requires-Dist: parsedatetime (>=2.6)
Requires-Dist: python-dateutil (>=2.8,<3.0)
Requires-Dist: pyxdg (>=0.27.0)
Requires-Dist: rich (>=12.2.0,<14.0.0)
Requires-Dist: ruamel.yaml (>=0.17.22)
Requires-Dist: tzlocal (>=4.0)
Project-URL: Documentation, https://jrnl.sh
Project-URL: Funding, https://opencollective.com/jrnl
Project-URL: Homepage, https://jrnl.sh
Project-URL: Issue Tracker, https://github.com/jrnl-org/jrnl/issues
Project-URL: Repository, https://github.com/jrnl-org/jrnl
